sudoku_py/__init__.py
sudoku_py/sudoku.py
sudoku_py-1.0.0.dist-info/LICENSE
sudoku_py-1.0.0.dist-info/METADATA
sudoku_py-1.0.0.dist-info/WHEEL
sudoku_py-1.0.0.dist-info/top_level.txt
sudoku_py-1.0.0.dist-info/RECORD
