Metadata-Version: 2.1
Name: sudoku-py
Version: 1.0.0
Summary: A Python Sudoku solver and generator
Home-page: https://github.com/Lenwee/sudoku-py
Author: Lewis Hammond
Author-email: lewishammond97@gmail.com
License: UNKNOWN
Platform: UNKNOWN
Classifier: Programming Language :: Python :: 3
Classifier: License :: OSI Approved :: MIT License
Classifier: Operating System :: OS Independent
Requires-Python: >=3.6
